fiat_tool/FIATClassificationDataset.py
fiat_tool/__init__.py
fiat_tool-0.7.0.11.dist-info/METADATA
fiat_tool-0.7.0.11.dist-info/WHEEL
fiat_tool-0.7.0.11.dist-info/top_level.txt
fiat_tool-0.7.0.11.dist-info/RECORD
