Metadata-Version: 2.1
Name: fiat-tool
Version: 0.7.0.11
Summary: Fast Image Annotation Tool, Free image labeling tool for deep learning
Home-page: https://github.com/gellston/FIAT-Release
Author: FIAT Development Team
Author-email: fiattool2022@gmail.com
License: MIT
Platform: UNKNOWN
Classifier: Topic :: Software Development :: Libraries
Classifier: License :: OSI Approved :: MIT License
Classifier: Programming Language :: Python :: 3.6
Requires-Python: >=3.6
Requires-Dist: numpy
Requires-Dist: opencv-python
Requires-Dist: torch-utils
Requires-Dist: torch
